topsis/__init__.py
topsis/topsis.py
topsisAnant102003755-1.2.dist-info/LICENSE.txt
topsisAnant102003755-1.2.dist-info/METADATA
topsisAnant102003755-1.2.dist-info/WHEEL
topsisAnant102003755-1.2.dist-info/entry_points.txt
topsisAnant102003755-1.2.dist-info/top_level.txt
topsisAnant102003755-1.2.dist-info/RECORD
